README.md
setup.py
search_optimization_tools/__init__.py
search_optimization_tools/routing.py
search_optimization_tools/structures.py
search_optimization_tools/utilities.py
search_optimization_tools.egg-info/PKG-INFO
search_optimization_tools.egg-info/SOURCES.txt
search_optimization_tools.egg-info/dependency_links.txt
search_optimization_tools.egg-info/requires.txt
search_optimization_tools.egg-info/top_level.txt