Metadata-Version: 2.1
Name: search-optimization-tools
Version: 0.0.1
Summary: UNKNOWN
Home-page: UNKNOWN
Author: Alaa Khamis and Yinan Wang
Author-email: yinanwang@sierra.one
License: MIT
Platform: UNKNOWN
Requires-Python: >=3.8,<3.9
